README.rst
setup.cfg
setup.py
src/ise/__init__.py
src/ise.pfgfieldpermission.egg-info/PKG-INFO
src/ise.pfgfieldpermission.egg-info/SOURCES.txt
src/ise.pfgfieldpermission.egg-info/dependency_links.txt
src/ise.pfgfieldpermission.egg-info/entry_points.txt
src/ise.pfgfieldpermission.egg-info/namespace_packages.txt
src/ise.pfgfieldpermission.egg-info/not-zip-safe
src/ise.pfgfieldpermission.egg-info/paster_plugins.txt
src/ise.pfgfieldpermission.egg-info/requires.txt
src/ise.pfgfieldpermission.egg-info/top_level.txt
src/ise/pfgfieldpermission/__init__.py
src/ise/pfgfieldpermission/config.py
src/ise/pfgfieldpermission/interfaces.py
src/ise/pfgfieldpermission/testing.py
src/ise/pfgfieldpermission/browser/__init__.py
src/ise/pfgfieldpermission/browser/fields.py
src/ise/pfgfieldpermission/content/__init__.py
src/ise/pfgfieldpermission/content/fields.py
src/ise/pfgfieldpermission/tests/__init__.py
src/ise/pfgfieldpermission/tests/test_example.py
src/ise/pfgfieldpermission/tests/test_robot.py