Metadata-Version: 1.1
Name: ise.pfgfieldpermission
Version: 1.0
Summary: Fields with permissions based on roles
Home-page: https://github.com/David-Kelterer/ise.pfgfieldpermission
Author: David Kelterer
Author-email: david.kelterer@ise.fraunhofer.de
License: gpl
Keywords: Plone PloneFormGen
Platform: UNKNOWN
Classifier: Environment :: Web Environment
Classifier: Framework :: Plone
Classifier: Operating System :: OS Independent
Classifier: Programming Language :: Python
Classifier: Programming Language :: Python :: 2.6
Classifier: Topic :: Software Development :: Libraries :: Python Modules
